pyopenms_viz/.gitignore
pyopenms_viz/__init__.py
pyopenms_viz/_config.py
pyopenms_viz/_core.py
pyopenms_viz/_misc.py
pyopenms_viz/constants.py
pyopenms_viz/_bokeh/__init__.py
pyopenms_viz/_bokeh/core.py
pyopenms_viz/_matplotlib/__init__.py
pyopenms_viz/_matplotlib/core.py
pyopenms_viz/_plotly/__init__.py
pyopenms_viz/_plotly/core.py
pyopenms_viz/assets/img/feature_boundary.png
pyopenms_viz/assets/img/peak_boundary.png
pyopenms_viz/test/test_data/README.md
pyopenms_viz/testing/BokehSnapshotExtension.py
pyopenms_viz/testing/BokehSnapshotExtension_JSON.py
pyopenms_viz/testing/MatplotlibSnapshotExtension.py
pyopenms_viz/testing/NumpySnapshotExtension.py
pyopenms_viz/testing/PandasSnapshotExtension.py
pyopenms_viz/testing/PlotlySnapshotExtension.py
pyopenms_viz/testing/__init__.py
pyopenms_viz-0.1.6.dist-info/entry_points.txt
pyopenms_viz-0.1.6.dist-info/licenses/LICENSE
pyopenms_viz-0.1.6.dist-info/WHEEL
pyopenms_viz-0.1.6.dist-info/METADATA
pyopenms_viz-0.1.6.dist-info/RECORD
