Metadata-Version: 2.4
Name: pyopenms_viz
Version: 0.1.6
Summary: A package for visualizing mass spectrometry data using pandas dataframes
Requires-Python: >=3.10, <=3.13
Classifier: Intended Audience :: Science/Research
Classifier: License :: OSI Approved :: BSD License
Classifier: Operating System :: OS Independent
Classifier: Programming Language :: Python :: 3.10
Classifier: Programming Language :: Python :: 3.11
Classifier: Topic :: Scientific/Engineering :: Bio-Informatics
Classifier: Topic :: Scientific/Engineering :: Chemistry
License-File: LICENSE
Requires-Dist: pandas>=0.17
Requires-Dist: bokeh>=3.4.1 ; extra == "all"
Requires-Dist: plotly ; extra == "all"
Requires-Dist: matplotlib ; extra == "all"
Requires-Dist: bokeh>=3.4.1 ; extra == "bokeh"
Requires-Dist: sphinx ; extra == "docs"
Requires-Dist: sphinx-gallery ; extra == "docs"
Requires-Dist: sphinx-copybutton ; extra == "docs"
Requires-Dist: pydata_sphinx_theme ; extra == "docs"
Requires-Dist: nbsphinx ; extra == "docs"
Requires-Dist: rdkit ; extra == "docs"
Requires-Dist: cairosvg ; extra == "docs"
Requires-Dist: pymzml ; extra == "docs"
Requires-Dist: ipython ; extra == "docs"
Requires-Dist: ipykernel ; extra == "docs"
Requires-Dist: matplotlib ; extra == "matplotlib"
Requires-Dist: plotly ; extra == "plotly"
Requires-Dist: pytest ; extra == "testing"
Requires-Dist: syrupy ; extra == "testing"
Provides-Extra: all
Provides-Extra: bokeh
Provides-Extra: docs
Provides-Extra: matplotlib
Provides-Extra: plotly
Provides-Extra: testing
